ghm/__init__.py
ghm/cli.py
ghm-0.1.4.dist-info/entry_points.txt
ghm-0.1.4.dist-info/WHEEL
ghm-0.1.4.dist-info/METADATA
ghm-0.1.4.dist-info/RECORD
